MANIFEST.in
README.txt
setup.py
tzpos/__init__.py
tzpos/factory.py
tzpos/searcher.py
tzpos/test.py
tzpos/tzposdb.data
tzpos/utils.py
tzpos/utils2.py
tzpos/utils3.py
tzpos.egg-info/.DS_Store
tzpos.egg-info/PKG-INFO
tzpos.egg-info/SOURCES.txt
tzpos.egg-info/dependency_links.txt
tzpos.egg-info/not-zip-safe
tzpos.egg-info/requires.txt
tzpos.egg-info/top_level.txt