Metadata-Version: 1.1
Name: tzpos
Version: 0.1.7
Summary: Time zone name calculation from lon and lat database.
Home-page: https://bitbucket.org/gamikun/tzpos
Author: Gamaliel Espinoza Macedo
Author-email: gamaliel.espinoza@gmail.com
License: UNKNOWN
Platform: UNKNOWN
Classifier: Development Status :: 5 - Production/Stable
Classifier: Intended Audience :: Developers
Classifier: Natural Language :: English
Classifier: License :: OSI Approved :: Apache Software License
Classifier: Programming Language :: Python :: 2.6
Classifier: Programming Language :: Python :: 2.7
